README.md
setup.py
classmate/__init__.py
classmate/server.py
classmate.egg-info/PKG-INFO
classmate.egg-info/SOURCES.txt
classmate.egg-info/dependency_links.txt
classmate.egg-info/requires.txt
classmate.egg-info/top_level.txt
classmate/static/css/bootstrap.min.css
classmate/static/css/style.css
classmate/static/js/main.js
classmate/templates/assignments.html
classmate/templates/index.html
classmate/templates/submit.html