Metadata-Version: 2.1
Name: classmate
Version: 0.1.5
Summary: 一个基于 Python 的助学web系统
Author: linmy
Author-email: wzlinmiaoyan@163.com
Requires-Python: >=3.8
Requires-Dist: flask>=2.0.0
Requires-Dist: opencv-python>=4.1.2.30
Requires-Dist: numpy>=1.24.4
Requires-Dist: pillow>=8.0.0
Requires-Dist: werkzeug>=2.0.0
